{
    "Events": {
        "Current": [
            {
                "event": "GENSHIN CONCERT 2024 \"Melodies of an Endless Journey\"",
                "image": "https://static.wikia.nocookie.net/gensin-impact/images/4/48/GENSHIN_CONCERT_2024_-_Melodies_of_an_Endless_Journey.png/revision/latest/scale-to-width-down/250?cb=20241209091755",
                "duration": [
                    "September 05, 2024",
                    "March 22, 2025"
                ],
                "type": [
                    "In-Person",
                    "Live"
                ],
                "status": "Current",
                "page": "https://genshin-impact.fandom.com/wiki/Genshin_Concert/GENSHIN_CONCERT_2024_%22Melodies_of_an_Endless_Journey%22"
            },
            {
                "event": "Tapirus Somniator Chapter",
                "image": "https://static.wikia.nocookie.net/gensin-impact/images/b/bf/Tapirus_Somniator_Chapter_Event.png/revision/latest/scale-to-width-down/250?cb=20250210040856",
                "duration": [
                    "February 12, 2025",
                    "March 04, 2025"
                ],
                "type": [
                    "In-Game",
                    "Story Quest"
                ],
                "status": "Current",
                "page": "https://genshin-impact.fandom.com/wiki/Tapirus_Somniator_Chapter_(Event)"
            },
            {
                "event": "Test Run - Yumemizuki Mizuki, Sigewinne, Gorou, Sayu",
                "image": "https://static.wikia.nocookie.net/gensin-impact/images/8/83/Test_Run_-_Yumemizuki_Mizuki%2C_Sigewinne%2C_Gorou%2C_Sayu.png/revision/latest/scale-to-width-down/250?cb=20250212085107",
                "duration": [
                    "February 12, 2025",
                    "March 04, 2025"
                ],
                "type": [
                    "In-Game",
                    "Test Run"
                ],
                "status": "Current",
                "page": "https://genshin-impact.fandom.com/wiki/Test_Run_-_Character_Trial_Event/2025-02-12"
            },
            {
                "event": "Wondrous Reverie",
                "image": "https://static.wikia.nocookie.net/gensin-impact/images/9/91/Battle_Pass_Wondrous_Reverie.png/revision/latest/scale-to-width-down/250?cb=20250210040901",
                "duration": [
                    "February 12, 2025",
                    "March 24, 2025"
                ],
                "type": [
                    "In-Game",
                    "Battle Pass"
                ],
                "status": "Current",
                "page": "https://genshin-impact.fandom.com/wiki/Battle_Pass/Wondrous_Reverie"
            },
            {
                "event": "Travelers' Tales: Anthology Chapter",
                "image": "https://static.wikia.nocookie.net/gensin-impact/images/d/d2/Travelers%27_Tales_Anthology_Chapter.png/revision/latest/scale-to-width-down/250?cb=20250210040842",
                "duration": [
                    "February 12, 2025",
                    "March 25, 2025"
                ],
                "type": [
                    "In-Game"
                ],
                "status": "Current",
                "page": "https://genshin-impact.fandom.com/wiki/Travelers%27_Tales:_Anthology_Chapter"
            },
            {
                "event": "The Forge Realm's Temper: Clever Stratagems",
                "image": "https://static.wikia.nocookie.net/gensin-impact/images/8/88/The_Forge_Realm%27s_Temper_Clever_Stratagems_2025-02-12.png/revision/latest/scale-to-width-down/250?cb=20250210040858",
                "duration": [
                    "February 12, 2025",
                    "March 26, 2025"
                ],
                "type": [
                    "In-Game",
                    "The Forge Realm's Temper"
                ],
                "status": "Current",
                "page": "https://genshin-impact.fandom.com/wiki/The_Forge_Realm%27s_Temper/2025-02-12"
            },
            {
                "event": "Heated Battle Mode: Automatic Artistry",
                "image": "https://static.wikia.nocookie.net/gensin-impact/images/e/e2/Heated_Battle_Mode_Automatic_Artistry_2025-02-21.png/revision/latest/scale-to-width-down/250?cb=20250218050043",
                "duration": [
                    "February 21, 2025",
                    "March 17, 2025"
                ],
                "type": [
                    "In-Game",
                    "Heated Battle Mode"
                ],
                "status": "Current",
                "page": "https://genshin-impact.fandom.com/wiki/Heated_Battle_Mode/2025-02-21"
            },
            {
                "event": "Realm of Tempered Valor",
                "image": "https://static.wikia.nocookie.net/gensin-impact/images/7/7a/Realm_of_Tempered_Valor.png/revision/latest/scale-to-width-down/250?cb=20250222040213",
                "duration": [
                    "February 24, 2025",
                    "March 10, 2025"
                ],
                "type": [
                    "In-Game"
                ],
                "status": "Current",
                "page": "https://genshin-impact.fandom.com/wiki/Realm_of_Tempered_Valor"
            }
        ],
        "Upcoming": [
            {
                "event": "Invasive Fish Wrangler",
                "image": "https://static.wikia.nocookie.net/gensin-impact/images/9/9a/Invasive_Fish_Wrangler.png/revision/latest/scale-to-width-down/250?cb=20250303040141",
                "duration": [
                    "March 05, 2025",
                    "March 17, 2025"
                ],
                "type": [
                    "In-Game",
                    "Co-Op"
                ],
                "status": "Upcoming",
                "page": "https://genshin-impact.fandom.com/wiki/Invasive_Fish_Wrangler"
            },
            {
                "event": "Reel Ad-Venture",
                "image": "https://static.wikia.nocookie.net/gensin-impact/images/a/ac/Reel_Ad-Venture.png/revision/latest/scale-to-width-down/250?cb=20250124132012",
                "duration": [
                    "March 12, 2025",
                    "March 24, 2025"
                ],
                "type": [
                    "In-Game"
                ],
                "status": "Upcoming",
                "page": "https://genshin-impact.fandom.com/wiki/Reel_Ad-Venture"
            },
            {
                "event": "Ley Line Overflow 2025-03-17",
                "image": "https://static.wikia.nocookie.net/gensin-impact/images/c/cc/Ley_Line_Overflow.png/revision/latest/scale-to-width-down/250?cb=20220703201328",
                "duration": [
                    "March 17, 2025",
                    "March 24, 2025"
                ],
                "type": [
                    "In-Game"
                ],
                "status": "Upcoming",
                "page": "https://genshin-impact.fandom.com/wiki/Ley_Line_Overflow/2025-03-17"
            }
        ],
        "Permanent": [
            {
                "event": "Fate Foretold",
                "image": "https://static.wikia.nocookie.net/gensin-impact/images/5/54/Fate_Foretold.png/revision/latest/scale-to-width-down/250?cb=20231205032118",
                "duration": [
                    "September 28, 2020"
                ],
                "type": [
                    "In-Game",
                    "Indefinite"
                ],
                "status": "Permanent",
                "page": "https://genshin-impact.fandom.com/wiki/Fate_Foretold"
            },
            {
                "event": "Wings of Companionship",
                "image": "https://static.wikia.nocookie.net/gensin-impact/images/4/47/Wings_of_Companionship.jpg/revision/latest/scale-to-width-down/250?cb=20200929014824",
                "duration": [
                    "September 28, 2020"
                ],
                "type": [
                    "In-Game",
                    "Mail",
                    "Indefinite"
                ],
                "status": "Permanent",
                "page": "https://genshin-impact.fandom.com/wiki/Wings_of_Companionship_(Event)"
            },
            {
                "event": "Spiral Abyss Event - People's Choice",
                "image": "https://static.wikia.nocookie.net/gensin-impact/images/d/d7/People%27s_Choice.png/revision/latest/scale-to-width-down/250?cb=20231206081811",
                "duration": [
                    "September 28, 2020"
                ],
                "type": [
                    "In-Game",
                    "Spiral Abyss",
                    "Indefinite"
                ],
                "status": "Permanent",
                "page": "https://genshin-impact.fandom.com/wiki/People%27s_Choice"
            },
            {
                "event": "Baptism of Song",
                "image": "https://static.wikia.nocookie.net/gensin-impact/images/9/96/Baptism_of_Song.jpg/revision/latest/scale-to-width-down/250?cb=20201109202750",
                "duration": [
                    "November 11, 2020"
                ],
                "type": [
                    "In-Game",
                    "Archon Quest",
                    "Indefinite"
                ],
                "status": "Permanent",
                "page": "https://genshin-impact.fandom.com/wiki/Baptism_of_Song"
            },
            {
                "event": "Stellar Reunion",
                "image": "https://static.wikia.nocookie.net/gensin-impact/images/6/6a/Stellar_Reunion.jpg/revision/latest/scale-to-width-down/250?cb=20221118043937",
                "duration": [
                    "December 23, 2020"
                ],
                "type": [
                    "In-Game",
                    "Indefinite",
                    "Login"
                ],
                "status": "Permanent",
                "page": "https://genshin-impact.fandom.com/wiki/Stellar_Reunion"
            },
            {
                "event": "HoYoLAB Community Daily Check-In",
                "image": "https://static.wikia.nocookie.net/gensin-impact/images/8/81/HoYoLAB_Community_Daily_Check-In.png/revision/latest/scale-to-width-down/250?cb=20210301043650",
                "duration": [
                    "March 01, 2021"
                ],
                "type": [
                    "Web",
                    "Indefinite",
                    "Login"
                ],
                "status": "Permanent",
                "page": "https://genshin-impact.fandom.com/wiki/HoYoLAB_Community_Daily_Check-In"
            },
            {
                "event": "Curtain of Leaves - Spiral Abyss Challenge",
                "image": "https://static.wikia.nocookie.net/gensin-impact/images/2/21/Curtain_of_Leaves.png/revision/latest/scale-to-width-down/250?cb=20220926042026",
                "duration": [
                    "September 28, 2022"
                ],
                "type": [
                    "In-Game",
                    "Spiral Abyss",
                    "Indefinite"
                ],
                "status": "Permanent",
                "page": "https://genshin-impact.fandom.com/wiki/Curtain_of_Leaves"
            },
            {
                "event": "The Curtain Never Falls on Magic",
                "image": "https://static.wikia.nocookie.net/gensin-impact/images/f/ff/The_Curtain_Never_Falls_on_Magic.png/revision/latest/scale-to-width-down/250?cb=20230814041042",
                "duration": [
                    "August 16, 2023"
                ],
                "type": [
                    "In-Game",
                    "Indefinite"
                ],
                "status": "Permanent",
                "page": "https://genshin-impact.fandom.com/wiki/The_Curtain_Never_Falls_on_Magic"
            },
            {
                "event": "Genshin Impact and Discord Account Linking Now Available: Complete Discord Account Linking to Unlock More Game Info Display and One-Click Rewards",
                "image": "https://static.wikia.nocookie.net/gensin-impact/images/d/d1/Genshin_Impact_and_Discord_Account_Linking.png/revision/latest/scale-to-width-down/250?cb=20240820161303",
                "duration": [
                    "August 20, 2024"
                ],
                "type": [
                    "Web",
                    "Indefinite",
                    "Login"
                ],
                "status": "Permanent",
                "page": "https://genshin-impact.fandom.com/wiki/Genshin_Impact_and_Discord_Account_Linking"
            },
            {
                "event": "Turbo Twirly!",
                "image": "https://static.wikia.nocookie.net/gensin-impact/images/3/3d/Turbo_Twirly%21_Event.png/revision/latest/scale-to-width-down/250?cb=20240826041406",
                "duration": [
                    "August 28, 2024"
                ],
                "type": [
                    "In-Game",
                    "Archon Quest",
                    "Indefinite"
                ],
                "status": "Permanent",
                "page": "https://genshin-impact.fandom.com/wiki/Turbo_Twirly!"
            }
        ]
    },
    "Codes": {
        "activeCodes": [
            {
                "code": "XA4N66LAC349",
                "server": "All",
                "rewards": [
                    {
                        "name": "Mora",
                        "amount": "20,000",
                        "imageURL": "https://static.wikia.nocookie.net/gensin-impact/images/8/84/Item_Mora.png/revision/latest/scale-to-width-down/20?cb=20210106073715"
                    },
                    {
                        "name": "Fruit-Flavored Milk Candies",
                        "amount": "2",
                        "imageURL": "https://static.wikia.nocookie.net/gensin-impact/images/6/6a/Item_Fruit-Flavored_Milk_Candies.png/revision/latest/scale-to-width-down/20?cb=20241009022753"
                    },
                    {
                        "name": "Dreams of Healing",
                        "amount": "2",
                        "imageURL": "https://static.wikia.nocookie.net/gensin-impact/images/e/e5/Item_Dreams_of_Healing.png/revision/latest/scale-to-width-down/20?cb=20250212073921"
                    },
                    {
                        "name": "Impeccably Organized",
                        "amount": "2",
                        "imageURL": "https://static.wikia.nocookie.net/gensin-impact/images/0/06/Item_Impeccably_Organized.png/revision/latest/scale-to-width-down/20?cb=20240828173142"
                    }
                ],
                "duration": [
                    "Discovered: February 26, 2025",
                    ""
                ],
                "isExpired": false
            },
            {
                "code": "7B476N4TDJ6V",
                "server": "All",
                "rewards": [
                    {
                        "name": "Mora",
                        "amount": "20,000",
                        "imageURL": "https://static.wikia.nocookie.net/gensin-impact/images/8/84/Item_Mora.png/revision/latest/scale-to-width-down/20?cb=20210106073715"
                    },
                    {
                        "name": "Crepes Suzette",
                        "amount": "1",
                        "imageURL": "https://static.wikia.nocookie.net/gensin-impact/images/1/17/Item_Crepes_Suzette.png/revision/latest/scale-to-width-down/20?cb=20231002072041"
                    },
                    {
                        "name": "Cold Cut Platter",
                        "amount": "1",
                        "imageURL": "https://static.wikia.nocookie.net/gensin-impact/images/1/16/Item_Cold_Cut_Platter.png/revision/latest/scale-to-width-down/20?cb=20210416221537"
                    },
                    {
                        "name": "Tea Break Pancake",
                        "amount": "1",
                        "imageURL": "https://static.wikia.nocookie.net/gensin-impact/images/2/25/Item_Tea_Break_Pancake.png/revision/latest/scale-to-width-down/20?cb=20210417154511"
                    },
                    {
                        "name": "Matsutake Meat Rolls",
                        "amount": "1",
                        "imageURL": "https://static.wikia.nocookie.net/gensin-impact/images/1/15/Item_Matsutake_Meat_Rolls.png/revision/latest/scale-to-width-down/20?cb=20210415135143"
                    },
                    {
                        "name": "Sparkling Berry Juice",
                        "amount": "1",
                        "imageURL": "https://static.wikia.nocookie.net/gensin-impact/images/2/2f/Item_Sparkling_Berry_Juice.png/revision/latest/scale-to-width-down/20?cb=20220929193634"
                    },
                    {
                        "name": "Teyvat Fried Egg",
                        "amount": "2",
                        "imageURL": "https://static.wikia.nocookie.net/gensin-impact/images/2/20/Item_Teyvat_Fried_Egg.png/revision/latest/scale-to-width-down/20?cb=20210416223215"
                    }
                ],
                "duration": [
                    "Discovered: February 25, 2025",
                    ""
                ],
                "isExpired": false
            },
            {
                "code": "POKAPOKAGENSHIN",
                "server": "All",
                "rewards": [
                    {
                        "name": "Sea Ganoderma",
                        "amount": "5",
                        "imageURL": "https://static.wikia.nocookie.net/gensin-impact/images/6/6d/Item_Sea_Ganoderma.png/revision/latest/scale-to-width-down/20?cb=20210610205502"
                    },
                    {
                        "name": "Hero's Wit",
                        "amount": "3",
                        "imageURL": "https://static.wikia.nocookie.net/gensin-impact/images/2/26/Item_Hero%27s_Wit.png/revision/latest/scale-to-width-down/20?cb=20201116222208"
                    },
                    {
                        "name": "Dreams of Healing",
                        "amount": "1",
                        "imageURL": "https://static.wikia.nocookie.net/gensin-impact/images/e/e5/Item_Dreams_of_Healing.png/revision/latest/scale-to-width-down/20?cb=20250212073921"
                    },
                    {
                        "name": "Kageuchi Handguard",
                        "amount": "5",
                        "imageURL": "https://static.wikia.nocookie.net/gensin-impact/images/7/71/Item_Kageuchi_Handguard.png/revision/latest/scale-to-width-down/20?cb=20210721030121"
                    }
                ],
                "duration": [
                    "Discovered: February 21, 2025",
                    "Valid until: March 23, 2025"
                ],
                "isExpired": false
            },
            {
                "code": "RB5PPN4BV355",
                "server": "All",
                "rewards": [
                    {
                        "name": "Primogem",
                        "amount": "30",
                        "imageURL": "https://static.wikia.nocookie.net/gensin-impact/images/d/d4/Item_Primogem.png/revision/latest/scale-to-width-down/20?cb=20201117071158"
                    },
                    {
                        "name": "Sea Ganoderma",
                        "amount": "3",
                        "imageURL": "https://static.wikia.nocookie.net/gensin-impact/images/6/6d/Item_Sea_Ganoderma.png/revision/latest/scale-to-width-down/20?cb=20210610205502"
                    },
                    {
                        "name": "Mora",
                        "amount": "20,000",
                        "imageURL": "https://static.wikia.nocookie.net/gensin-impact/images/8/84/Item_Mora.png/revision/latest/scale-to-width-down/20?cb=20210106073715"
                    },
                    {
                        "name": "Adventurer's Experience",
                        "amount": "1",
                        "imageURL": "https://static.wikia.nocookie.net/gensin-impact/images/0/07/Item_Adventurer%27s_Experience.png/revision/latest/scale-to-width-down/20?cb=20201116222310"
                    }
                ],
                "duration": [
                    "Discovered: February 17, 2025",
                    ""
                ],
                "isExpired": false
            },
            {
                "code": "11KU0MNDK2RG",
                "server": "All",
                "rewards": [
                    {
                        "name": "Primogem",
                        "amount": "60",
                        "imageURL": "https://static.wikia.nocookie.net/gensin-impact/images/d/d4/Item_Primogem.png/revision/latest/scale-to-width-down/20?cb=20201117071158"
                    },
                    {
                        "name": "Adventurer's Experience",
                        "amount": "5",
                        "imageURL": "https://static.wikia.nocookie.net/gensin-impact/images/0/07/Item_Adventurer%27s_Experience.png/revision/latest/scale-to-width-down/20?cb=20201116222310"
                    }
                ],
                "duration": [
                    "Discovered: February 7, 2025",
                    ""
                ],
                "isExpired": false
            },
            {
                "code": "HNYM49IX9PDS",
                "server": "All",
                "rewards": [
                    {
                        "name": "Primogem",
                        "amount": "60",
                        "imageURL": "https://static.wikia.nocookie.net/gensin-impact/images/d/d4/Item_Primogem.png/revision/latest/scale-to-width-down/20?cb=20201117071158"
                    },
                    {
                        "name": "Adventurer's Experience",
                        "amount": "5",
                        "imageURL": "https://static.wikia.nocookie.net/gensin-impact/images/0/07/Item_Adventurer%27s_Experience.png/revision/latest/scale-to-width-down/20?cb=20201116222310"
                    }
                ],
                "duration": [
                    "Discovered: January 5, 2025",
                    "Valid until: March 6, 2025"
                ],
                "isExpired": false
            },
            {
                "code": "GENSHINGIFT",
                "server": "All",
                "rewards": [
                    {
                        "name": "Primogem",
                        "amount": "50",
                        "imageURL": "https://static.wikia.nocookie.net/gensin-impact/images/d/d4/Item_Primogem.png/revision/latest/scale-to-width-down/20?cb=20201117071158"
                    },
                    {
                        "name": "Hero's Wit",
                        "amount": "3",
                        "imageURL": "https://static.wikia.nocookie.net/gensin-impact/images/2/26/Item_Hero%27s_Wit.png/revision/latest/scale-to-width-down/20?cb=20201116222208"
                    }
                ],
                "duration": [
                    "Discovered: November 10, 2020",
                    "Valid: (indefinite)"
                ],
                "isExpired": false
            }
        ],
        "expiredCodes": []
    }
}